dirlin/__init__.py
dirlin/main.py
dirlin/setup.py
dirlin/src/__init__.py
dirlin/src/base.py
dirlin-0.1.17.dist-info/LICENSE.txt
dirlin-0.1.17.dist-info/METADATA
dirlin-0.1.17.dist-info/WHEEL
dirlin-0.1.17.dist-info/RECORD
