Metadata-Version: 2.1
Name: Dirlin
Version: 0.1.17
Summary: Handy functions for local files
Author: mendozasho
Requires-Python: >=3.11,<4.0
Classifier: Programming Language :: Python :: 3
Classifier: Programming Language :: Python :: 3.11
Classifier: Programming Language :: Python :: 3.12
Requires-Dist: chardet (==5.2.0)
Requires-Dist: numpy (==2.0.0)
Requires-Dist: openpyxl (==3.1.2)
Requires-Dist: pandas (==2.2.2)
Requires-Dist: pathlib (==1.0.1)
Requires-Dist: pyxlsb (==1.0.10)
Requires-Dist: xlrd (==2.0.1)
